
<testcases>
    <param name="server_tonydev" value="http://www.wall150ans.com" />

    <case>
        <add_header>Authorization: Basic d2FsbDE1MGFuczpseUw1WC5UcWJ5OEc=</add_header>
        <url>${server_tonydev}/testvideo/video.php</url>
    </case>

   <!--<case>-->
       <!--<url>${server_tonydev}/node/PostByMail</url>-->
       <!--<method>POST</method>-->
       <!--<add_header>Content-Type: multipart/form-data</add_header>-->
       <!--<add_header>Authorization: Basic d2FsbDE1MGFuczpseUw1WC5UcWJ5OEc=</add_header>-->
       <!--<body><![CDATA[desc=testavideo&user=tony@fuel-it-up.com&photo=@file/Users/Tony1/Downloads/sg test material/01_07_filtering.mov]]></body>-->
   <!--</case>-->
   
</testcases>
